RobotFramework_TestsuitesManagement/RobotFramework_TestsuitesManagement.pdf
RobotFramework_TestsuitesManagement/__init__.py
RobotFramework_TestsuitesManagement/version.py
RobotFramework_TestsuitesManagement/Config/__init__.py
RobotFramework_TestsuitesManagement/Config/config.py
RobotFramework_TestsuitesManagement/Config/configuration_schema.json
RobotFramework_TestsuitesManagement/Config/robot_config.jsonp
RobotFramework_TestsuitesManagement/Keywords/__init__.py
RobotFramework_TestsuitesManagement/Keywords/key_words.py
RobotFramework_TestsuitesManagement/Keywords/on_failure_handle.py
RobotFramework_TestsuitesManagement/Utils/__init__.py
RobotFramework_TestsuitesManagement/Utils/app_config.py
RobotFramework_TestsuitesManagement/Utils/app_logger.py
RobotFramework_TestsuitesManagement/Utils/lib_listener.py
RobotFramework_TestsuitesManagement/Utils/struct.py
RobotFramework_TestsuitesManagement/Utils/version.py
RobotFramework_TestsuitesManagement/Utils/Events/__init__.py
RobotFramework_TestsuitesManagement/Utils/Events/event.py
RobotFramework_TestsuitesManagement/Utils/Events/scope_event.py
robotframework_testsuitesmanagement-0.9.1.dist-info/licenses/LICENSE
robotframework_testsuitesmanagement-0.9.1.dist-info/METADATA
robotframework_testsuitesmanagement-0.9.1.dist-info/WHEEL
robotframework_testsuitesmanagement-0.9.1.dist-info/entry_points.txt
robotframework_testsuitesmanagement-0.9.1.dist-info/top_level.txt
robotframework_testsuitesmanagement-0.9.1.dist-info/RECORD
