Metadata-Version: 2.4
Name: robotframework-testsuitesmanagement
Version: 0.9.1
Summary: Functionality to manage RobotFramework testsuites
Home-page: https://github.com/test-fullautomation/robotframework-testsuitesmanagement
Author: Mai Dinh Nam Son
Author-email: son.maidinhnam@vn.bosch.com
Classifier: Programming Language :: Python :: 3
Classifier: License :: OSI Approved :: Apache Software License
Classifier: Operating System :: OS Independent
Classifier: Development Status :: 4 - Beta
Classifier: Intended Audience :: Developers
Classifier: Topic :: Software Development
Requires-Python: >=3.0
License-File: LICENSE
Requires-Dist: JsonPreprocessor
Requires-Dist: dotdict
Requires-Dist: robotframework
Requires-Dist: robotframework-pythonlibcore
Requires-Dist: jsonschema
Requires-Dist: lxml
Requires-Dist: regex
Dynamic: author
Dynamic: author-email
Dynamic: classifier
Dynamic: description
Dynamic: description-content-type
Dynamic: home-page
Dynamic: license-file
Dynamic: requires-dist
Dynamic: requires-python
Dynamic: summary
